pymkdocs/__init__.py
pymkdocs/_version.py
pymkdocs/main.py
pymkdocs/pymkdocs.py
pymkdocs-0.4.0.0.dist-info/LICENCE
pymkdocs-0.4.0.0.dist-info/METADATA
pymkdocs-0.4.0.0.dist-info/WHEEL
pymkdocs-0.4.0.0.dist-info/entry_points.txt
pymkdocs-0.4.0.0.dist-info/top_level.txt
pymkdocs-0.4.0.0.dist-info/RECORD
