Metadata-Version: 2.1
Name: pymkdocs
Version: 0.4.0.0
Summary: Documentation generator for Python, using markdown and MkDocs.
Home-page: UNKNOWN
Author: BuvinJ
Author-email: buvintech@gmail.com
License: UNKNOWN
Platform: UNKNOWN
Classifier: Development Status :: 3 - Alpha
Classifier: Programming Language :: Python :: 3
Classifier: License :: OSI Approved :: MIT License
Classifier: Operating System :: OS Independent
Classifier: Intended Audience :: Developers
Classifier: Topic :: Documentation
Requires-Dist: mkdocs
Requires-Dist: mkdocs-material
Requires-Dist: pymdown-extensions
